firex_bundle_ci/__init__.py
firex_bundle_ci/_version.py
firex_bundle_ci/tasks.py
firex_bundle_ci/versioneer.py
firex_bundle_ci-1.4.3.dist-info/LICENSE
firex_bundle_ci-1.4.3.dist-info/METADATA
firex_bundle_ci-1.4.3.dist-info/WHEEL
firex_bundle_ci-1.4.3.dist-info/entry_points.txt
firex_bundle_ci-1.4.3.dist-info/top_level.txt
firex_bundle_ci-1.4.3.dist-info/zip-safe
firex_bundle_ci-1.4.3.dist-info/RECORD
