Metadata-Version: 2.1
Name: firex-bundle-ci
Version: 1.4.3
Summary: FireX CI services
Home-page: https://github.com/FireXStuff/firex-bundle-ci.git
Author: Core FireX Team
Author-email: firex-dev@gmail.com
License: BSD-3-Clause
License-File: LICENSE
Requires-Dist: firexapp
Requires-Dist: firex-keeper
Requires-Dist: firex-flame
Requires-Dist: lxml
Requires-Dist: xunitmerge
Requires-Dist: unittest-xml-reporting
